setup.py
ctpbee_cta/__init__.py
ctpbee_cta/constant.py
ctpbee_cta/cta.py
ctpbee_cta/handler.py
ctpbee_cta/indicator.py
ctpbee_cta.egg-info/PKG-INFO
ctpbee_cta.egg-info/SOURCES.txt
ctpbee_cta.egg-info/dependency_links.txt
ctpbee_cta.egg-info/requires.txt
ctpbee_cta.egg-info/top_level.txt