Metadata-Version: 1.0
Name: ctpbee-cta
Version: 0.11
Summary: ctpbee cta strategy support
Home-page: https://github.com/ctpbee/ctpbee_cta
Author: somewheve
Author-email: somewheve@gmail.com
License: MIT
Platform: Windows
Platform: Linux
Platform: Mac OS-X
